zentra_api/auth/__init__.py
zentra_api/auth/context.py
zentra_api/auth/enums.py
zentra_api/auth/security.py
zentra_api/cli/__init__.py
zentra_api/cli/builder/__init__.py
zentra_api/cli/builder/poetry.py
zentra_api/cli/builder/routes.py
zentra_api/cli/commands/__init__.py
zentra_api/cli/commands/add.py
zentra_api/cli/commands/build.py
zentra_api/cli/commands/setup.py
zentra_api/cli/conf/__init__.py
zentra_api/cli/conf/checks.py
zentra_api/cli/conf/logger.py
zentra_api/cli/constants/__init__.py
zentra_api/cli/constants/display.py
zentra_api/cli/constants/enums.py
zentra_api/cli/constants/message.py
zentra_api/cli/constants/models.py
zentra_api/cli/constants/routes.py
zentra_api/cli/main.py
zentra_api/cli/template/fastapi/deployment/.dockerignore
zentra_api/cli/template/fastapi/deployment/Dockerfile.backend
zentra_api/cli/template/fastapi/deployment/docker-compose.yml
zentra_api/cli/template/fastapi/deployment/railway.toml
zentra_api/cli/template/fastapi/project/.coveragerc
zentra_api/cli/template/fastapi/project/.env.template
zentra_api/cli/template/fastapi/project/README.md
zentra_api/cli/template/fastapi/project/alembic.ini
zentra_api/cli/template/fastapi/project/app/__init__.py
zentra_api/cli/template/fastapi/project/app/api/__init__.py
zentra_api/cli/template/fastapi/project/app/auth/__init__.py
zentra_api/cli/template/fastapi/project/app/auth/response.py
zentra_api/cli/template/fastapi/project/app/auth/schema.py
zentra_api/cli/template/fastapi/project/app/core/__init__.py
zentra_api/cli/template/fastapi/project/app/core/config.py
zentra_api/cli/template/fastapi/project/app/core/db.py
zentra_api/cli/template/fastapi/project/app/core/dependencies.py
zentra_api/cli/template/fastapi/project/app/db_models/__init__.py
zentra_api/cli/template/fastapi/project/app/db_models/user.py
zentra_api/cli/template/fastapi/project/app/main.py
zentra_api/cli/template/fastapi/project/migrations/README
zentra_api/cli/template/fastapi/project/migrations/env.py
zentra_api-0.1.14.dist-info/LICENSE
zentra_api-0.1.14.dist-info/METADATA
zentra_api-0.1.14.dist-info/WHEEL
zentra_api-0.1.14.dist-info/entry_points.txt
zentra_api-0.1.14.dist-info/RECORD
