Metadata-Version: 2.1
Name: zentra_api
Version: 0.1.14
Summary: A CLI tool for building FastAPI apps faster.
Home-page: https://zentra.achronus.dev/api
License: MIT
Author: Ryan Partridge
Author-email: rpartridge101@gmail.com
Requires-Python: >=3.12,<4.0
Classifier: Development Status :: 3 - Alpha
Classifier: Environment :: Console
Classifier: Framework :: FastAPI
Classifier: Intended Audience :: Developers
Classifier: License :: OSI Approved :: MIT License
Classifier: Natural Language :: English
Classifier: Programming Language :: Python
Classifier: Programming Language :: Python :: 3
Classifier: Programming Language :: Python :: 3.12
Classifier: Topic :: Software Development :: Libraries :: Application Frameworks
Requires-Dist: bcrypt (>=4.2,<5.0)
Requires-Dist: fastapi[standard] (>=0.114,<0.115)
Requires-Dist: inflect (>=7.4,<8.0)
Requires-Dist: pydantic (>=2.9,<3.0)
Requires-Dist: sqlalchemy (>=2.0,<3.0)
Requires-Dist: toml (>=0.10,<0.11)
Requires-Dist: typer (>=0.12,<0.13)
Project-URL: Documentation, https://zentra.achronus.dev/api
Project-URL: Repository, https://github.com/Achronus/zentra-api
Project-URL: issues, https://github.com/Achronus/zentra-api/issues
